planar/__init__.py
planar/__init__.pyi
planar/box.py
planar/box.pyi
planar/line.py
planar/line.pyi
planar/polygon.py
planar/polygon.pyi
planar/py.py
planar/py.pyi
planar/py.typed
planar/transform.py
planar/transform.pyi
planar/util.py
planar/util.pyi
planar/vector.py
planar/vector.pyi
planar/test/__init__.py
planar/test/test_box.py
planar/test/test_line.py
planar/test/test_planar.py
planar/test/test_polygon.py
planar/test/test_transform.py
planar/test/test_util.py
planar/test/test_vector.py
chalk_planar-0.4.dist-info/LICENSE.txt
chalk_planar-0.4.dist-info/METADATA
chalk_planar-0.4.dist-info/WHEEL
chalk_planar-0.4.dist-info/top_level.txt
chalk_planar-0.4.dist-info/RECORD
